Metadata-Version: 1.0
Name: alfajor
Version: 0.1
Summary: Tasty functional testing.
Home-page: http://github.com/idealistdev/alfajor/
Author: Action Without Borders, Inc.
Author-email: jason@idealist.org
License: BSD
Keywords: testing test functional integration browser ajax selenium
Platform: UNKNOWN
Classifier: Development Status :: 1 - Planning
Classifier: Intended Audience :: Developers
Classifier: License :: OSI Approved :: BSD License
Classifier: Operating System :: OS Independent
Classifier: Programming Language :: Python
Classifier: Programming Language :: Python :: 2
Classifier: Programming Language :: Python :: 2.5
Classifier: Programming Language :: Python :: 2.6
Classifier: Programming Language :: Python :: 2.7
Classifier: Topic :: Internet :: WWW/HTTP
Classifier: Topic :: Internet :: WWW/HTTP :: Browsers
Classifier: Topic :: Software Development :: Testing
Classifier: Topic :: Software Development :: Quality Assurance
